paphra_table/__init__.py
paphra_table/__main__.py
paphra_table/table.py
paphra_table-1.0.3.dist-info/LICENSE.txt
paphra_table-1.0.3.dist-info/METADATA
paphra_table-1.0.3.dist-info/WHEEL
paphra_table-1.0.3.dist-info/top_level.txt
paphra_table-1.0.3.dist-info/RECORD
