Metadata-Version: 2.1
Name: paphra-table
Version: 1.0.3
Summary: Python Table. Designed to give the user the control over tables in Python
Home-page: http://github.com/Paphra/PythonTable/
Author: Epaphradito Lugayavu
Author-email: paphra.me@gmail.com
License: LICENSE.txt
Platform: UNKNOWN
Classifier: Programming Language :: Python :: 3
Classifier: Operating System :: OS Independent
